{"index": "Clint", "main_category": "NPCGiftTastes", "strings": "0 -20 -21 92 110 111 112 142 152 153 157 178 105 168 170 171 172 374 376 378 380 397 420 684 721 766 767 772 203 308 265", "loveText": "没错！我一直在找的就是这个！", "love": "{'64', '70', '749', '66', '337', '279', '373', '649', '797', '446', '68', '336', '605', '74', '60', '62'}", "like": "{'-75', '-80', '636', '-26', '459', '335', '634', '72', '395', '-7', '724', '334', '613', '638', '-2', '635', '637'}", "neutral": "{'194', '216', '304', '262', '-15'}", "dislike": "{'', '726', '423', '-80', '311', '535', '-4', '-74', '536', '-25', '749', '537', '80', '247', '309', '169', '2', '-19', '305', '-15', '-16', '310', '-22', '419', '-24', '16', '-8', '78', '725', '246', '403', '-12', '-28'}", "hate": "{'772', '376', '111', '171', '110', '766', '203', '721', '170', '152', '397', '-21', '0', '142', '172', '380', '157', '420', '153', '374', '684', '767', '112', '105', '378', '178', '4', '168', '92', '308', '265', '-20'}", "loveIndex": "60 62 64 66 68 70 336 337 605 649 749", "likeText": "有趣的礼物。谢谢！", "likeIndex": "334 335", "dislikeText": "*唉*……", "dislikeIndex": "-80 2 16 80 ", "hateText": "这让我很失望。", "hateIndex": "4", "neutralText": "谢谢你啊。", "neutralIndex": "-15", "unresolved_0": ""}