{"index": "Penny", "main_category": "NPCGiftTastes", "strings": "0 -20 -21 92 110 111 112 142 152 153 157 178 105 168 170 171 172 374 376 378 380 397 420 684 721 766 767 772 203 308 265", "loveText": "非常感谢！我太喜欢这个了！", "love": "{'254', '797', '218', '376', '244', '279', '164', '446', '74', '373', '72', '60', '230', '651'}", "like": "{'724', '-6', '22', '20', '613', '-75', '-80', '72', '-7', '635', '-2', '634', '395', '638', '459', '637', '636', '-26'}", "neutral": "{'', '262', '304', '194', '216'}", "dislike": "{'-22', '440', '-12', '-15', '-24', '309', '725', '-16', '423', '403', '456', '246', '422', '247', '-8', '420', '-19', '330', '726', '80', '536', '169', '537', '-28', '-25', '78', '535', '457', '305', '311', '310', '749', '-4', '444', '-74', '419'}", "hate": "{'157', '380', '397', '446', '153', '111', '178', '110', '376', '459', '152', '766', '767', '398', '112', '420', '0', '684', '168', '170', '203', '308', '348', '346', '374', '303', '105', '172', '171', '-20', '378', '721', '304', '772', '-21', '92', '265', '142'}", "loveIndex": "60 376 651 72 164 218 230 244 254", "likeText": "非常感谢！这看起来很特别。", "likeIndex": "-6 20 22", "dislikeText": "呃，给我的？……谢谢。", "dislikeIndex": "-4 80 330 456 457 444 440 422 420", "hateText": "啊……抱歉，但是我真的很讨厌这个。", "hateIndex": "446 346 348 303 304 398 459", "neutralText": "谢谢，这看起来不错。", "neutralIndex": "", "unresolved_0": ""}